primalbedtools/__init__.py
primalbedtools/amplicons.py
primalbedtools/bedfiles.py
primalbedtools/errors.py
primalbedtools/fasta.py
primalbedtools/main.py
primalbedtools/remap.py
primalbedtools/scheme.py
primalbedtools/utils.py
primalbedtools/validate.py
primalbedtools-1.0.0.dist-info/METADATA
primalbedtools-1.0.0.dist-info/WHEEL
primalbedtools-1.0.0.dist-info/entry_points.txt
primalbedtools-1.0.0.dist-info/licenses/LICENSE
primalbedtools-1.0.0.dist-info/RECORD
