Metadata-Version: 2.4
Name: primalbedtools
Version: 1.0.0
Summary: A collection of tools for working with primer.bed files
Project-URL: Repository, https://github.com/ChrisgKent/primalbedtools
Author-email: ChrisKent <chrisgkent@gmail.com>
License-Expression: MIT
License-File: LICENSE
Requires-Python: <4,>=3.9
